CHANGES.txt
MANIFEST.in
README.md
setup.py
pyramid_command/__init__.py
pyramid_command.egg-info/PKG-INFO
pyramid_command.egg-info/SOURCES.txt
pyramid_command.egg-info/dependency_links.txt
pyramid_command.egg-info/entry_points.txt
pyramid_command.egg-info/not-zip-safe
pyramid_command.egg-info/top_level.txt